{
  "config": {
    "configFile": "/home/user/ScholarSync-/qa/playwright.config.ts",
    "rootDir": "/home/user/ScholarSync-/qa/generated",
    "forbidOnly": true,
    "fullyParallel": false,
    "globalSetup": null,
    "globalTeardown": null,
    "globalTimeout": 0,
    "grep": {},
    "grepInvert": null,
    "maxFailures": 0,
    "metadata": {
      "actualWorkers": 1
    },
    "preserveOutput": "always",
    "reporter": [
      [
        "json",
        {
          "outputFile": "./progress/results.json"
        }
      ],
      [
        "list",
        null
      ]
    ],
    "reportSlowTests": {
      "max": 5,
      "threshold": 300000
    },
    "quiet": false,
    "projects": [
      {
        "outputDir": "/home/user/ScholarSync-/test-results",
        "repeatEach": 1,
        "retries": 0,
        "metadata": {
          "actualWorkers": 1
        },
        "id": "qa-chromium",
        "name": "qa-chromium",
        "testDir": "/home/user/ScholarSync-/qa/generated",
        "testIgnore": [],
        "testMatch": [
          "**/*.@(spec|test).?(c|m)[jt]s?(x)"
        ],
        "timeout": 60000
      }
    ],
    "shard": null,
    "updateSnapshots": "missing",
    "updateSourceMethod": "patch",
    "version": "1.56.1",
    "workers": 1,
    "webServer": {
      "command": "PORT=3001 npm run dev",
      "port": 3001,
      "reuseExistingServer": true,
      "timeout": 120000,
      "stdout": "pipe",
      "stderr": "pipe"
    }
  },
  "suites": [
    {
      "title": "compliance/spec-016.spec.ts",
      "file": "compliance/spec-016.spec.ts",
      "column": 0,
      "line": 0,
      "specs": [],
      "suites": [
        {
          "title": "compliance / spec-016",
          "file": "compliance/spec-016.spec.ts",
          "line": 36,
          "column": 6,
          "specs": [
            {
              "title": "cp-000: Realtime score updates have no aria-live announcement",
              "ok": true,
              "tags": [],
              "tests": [
                {
                  "timeout": 60000,
                  "annotations": [],
                  "expectedStatus": "passed",
                  "projectId": "qa-chromium",
                  "projectName": "qa-chromium",
                  "results": [
                    {
                      "workerIndex": 0,
                      "parallelIndex": 0,
                      "status": "passed",
                      "duration": 6494,
                      "errors": [],
                      "stdout": [],
                      "stderr": [],
                      "retry": 0,
                      "startTime": "2026-03-16T02:44:41.933Z",
                      "annotations": [],
                      "attachments": [
                        {
                          "name": "screenshot",
                          "contentType": "image/png",
                          "path": "/home/user/ScholarSync-/test-results/compliance-spec-016-compli-6fcfe-e-no-aria-live-announcement-qa-chromium/test-finished-1.png"
                        }
                      ]
                    }
                  ],
                  "status": "expected"
                }
              ],
              "id": "f49594e98bf0294642a8-e0f1e9025f0ce6a70cc0",
              "file": "compliance/spec-016.spec.ts",
              "line": 49,
              "column": 3
            },
            {
              "title": "cp-001: Copyleaks scan progress has no aria-busy or aria-live indicator",
              "ok": true,
              "tags": [],
              "tests": [
                {
                  "timeout": 60000,
                  "annotations": [],
                  "expectedStatus": "passed",
                  "projectId": "qa-chromium",
                  "projectName": "qa-chromium",
                  "results": [
                    {
                      "workerIndex": 0,
                      "parallelIndex": 0,
                      "status": "passed",
                      "duration": 1582,
                      "errors": [],
                      "stdout": [],
                      "stderr": [],
                      "retry": 0,
                      "startTime": "2026-03-16T02:44:48.503Z",
                      "annotations": [],
                      "attachments": [
                        {
                          "name": "screenshot",
                          "contentType": "image/png",
                          "path": "/home/user/ScholarSync-/test-results/compliance-spec-016-compli-1dec2-busy-or-aria-live-indicator-qa-chromium/test-finished-1.png"
                        }
                      ]
                    }
                  ],
                  "status": "expected"
                }
              ],
              "id": "f49594e98bf0294642a8-7d64429182b89df8e254",
              "file": "compliance/spec-016.spec.ts",
              "line": 99,
              "column": 3
            },
            {
              "title": "cp-002: srcappapiintegrity-checkbatchroutets still lacks checklist coverage for several ",
              "ok": true,
              "tags": [],
              "tests": [
                {
                  "timeout": 60000,
                  "annotations": [],
                  "expectedStatus": "passed",
                  "projectId": "qa-chromium",
                  "projectName": "qa-chromium",
                  "results": [
                    {
                      "workerIndex": 0,
                      "parallelIndex": 0,
                      "status": "passed",
                      "duration": 1609,
                      "errors": [],
                      "stdout": [],
                      "stderr": [],
                      "retry": 0,
                      "startTime": "2026-03-16T02:44:50.102Z",
                      "annotations": [],
                      "attachments": [
                        {
                          "name": "screenshot",
                          "contentType": "image/png",
                          "path": "/home/user/ScholarSync-/test-results/compliance-spec-016-compli-f9859-klist-coverage-for-several--qa-chromium/test-finished-1.png"
                        }
                      ]
                    }
                  ],
                  "status": "expected"
                }
              ],
              "id": "f49594e98bf0294642a8-121257df7c964cb30e67",
              "file": "compliance/spec-016.spec.ts",
              "line": 149,
              "column": 3
            },
            {
              "title": "cp-003: srcappapiintegrity-checkhistoryroutets clamps limit into 1100 clamps offset to 0",
              "ok": true,
              "tags": [],
              "tests": [
                {
                  "timeout": 60000,
                  "annotations": [],
                  "expectedStatus": "passed",
                  "projectId": "qa-chromium",
                  "projectName": "qa-chromium",
                  "results": [
                    {
                      "workerIndex": 0,
                      "parallelIndex": 0,
                      "status": "passed",
                      "duration": 1568,
                      "errors": [],
                      "stdout": [],
                      "stderr": [],
                      "retry": 0,
                      "startTime": "2026-03-16T02:44:51.721Z",
                      "annotations": [],
                      "attachments": [
                        {
                          "name": "screenshot",
                          "contentType": "image/png",
                          "path": "/home/user/ScholarSync-/test-results/compliance-spec-016-compli-f2466-nto-1100-clamps-offset-to-0-qa-chromium/test-finished-1.png"
                        }
                      ]
                    }
                  ],
                  "status": "expected"
                }
              ],
              "id": "f49594e98bf0294642a8-b3625e7509de474838ce",
              "file": "compliance/spec-016.spec.ts",
              "line": 199,
              "column": 3
            },
            {
              "title": "cp-004: The project-dropdown outside-click effect removes its document mousedown listene",
              "ok": true,
              "tags": [],
              "tests": [
                {
                  "timeout": 60000,
                  "annotations": [],
                  "expectedStatus": "passed",
                  "projectId": "qa-chromium",
                  "projectName": "qa-chromium",
                  "results": [
                    {
                      "workerIndex": 0,
                      "parallelIndex": 0,
                      "status": "passed",
                      "duration": 1558,
                      "errors": [],
                      "stdout": [],
                      "stderr": [],
                      "retry": 0,
                      "startTime": "2026-03-16T02:44:53.302Z",
                      "annotations": [],
                      "attachments": [
                        {
                          "name": "screenshot",
                          "contentType": "image/png",
                          "path": "/home/user/ScholarSync-/test-results/compliance-spec-016-compli-ccf31--document-mousedown-listene-qa-chromium/test-finished-1.png"
                        }
                      ]
                    }
                  ],
                  "status": "expected"
                }
              ],
              "id": "f49594e98bf0294642a8-aec2fbe0a5d4f414b091",
              "file": "compliance/spec-016.spec.ts",
              "line": 249,
              "column": 3
            },
            {
              "title": "cp-005: Route-level recovery coverage is still shallow srccomponentsuierror-displaytsx c",
              "ok": true,
              "tags": [],
              "tests": [
                {
                  "timeout": 60000,
                  "annotations": [],
                  "expectedStatus": "passed",
                  "projectId": "qa-chromium",
                  "projectName": "qa-chromium",
                  "results": [
                    {
                      "workerIndex": 0,
                      "parallelIndex": 0,
                      "status": "passed",
                      "duration": 1558,
                      "errors": [],
                      "stdout": [],
                      "stderr": [],
                      "retry": 0,
                      "startTime": "2026-03-16T02:44:54.871Z",
                      "annotations": [],
                      "attachments": [
                        {
                          "name": "screenshot",
                          "contentType": "image/png",
                          "path": "/home/user/ScholarSync-/test-results/compliance-spec-016-compli-b7d15-ponentsuierror-displaytsx-c-qa-chromium/test-finished-1.png"
                        }
                      ]
                    }
                  ],
                  "status": "expected"
                }
              ],
              "id": "f49594e98bf0294642a8-a40cec46eed0217497a4",
              "file": "compliance/spec-016.spec.ts",
              "line": 299,
              "column": 3
            },
            {
              "title": "cp-006: The app-wide fallback srcappglobal-errortsx also captures errors to Sentry and r",
              "ok": true,
              "tags": [],
              "tests": [
                {
                  "timeout": 60000,
                  "annotations": [],
                  "expectedStatus": "passed",
                  "projectId": "qa-chromium",
                  "projectName": "qa-chromium",
                  "results": [
                    {
                      "workerIndex": 0,
                      "parallelIndex": 0,
                      "status": "passed",
                      "duration": 1579,
                      "errors": [],
                      "stdout": [],
                      "stderr": [],
                      "retry": 0,
                      "startTime": "2026-03-16T02:44:56.437Z",
                      "annotations": [],
                      "attachments": [
                        {
                          "name": "screenshot",
                          "contentType": "image/png",
                          "path": "/home/user/ScholarSync-/test-results/compliance-spec-016-compli-4687c-ures-errors-to-Sentry-and-r-qa-chromium/test-finished-1.png"
                        }
                      ]
                    }
                  ],
                  "status": "expected"
                }
              ],
              "id": "f49594e98bf0294642a8-d9e879d2dfcf52d47ef3",
              "file": "compliance/spec-016.spec.ts",
              "line": 349,
              "column": 3
            },
            {
              "title": "cp-007: The document-loading effect in srcappappcompliancepagetsx has no stale-response ",
              "ok": true,
              "tags": [],
              "tests": [
                {
                  "timeout": 60000,
                  "annotations": [],
                  "expectedStatus": "passed",
                  "projectId": "qa-chromium",
                  "projectName": "qa-chromium",
                  "results": [
                    {
                      "workerIndex": 0,
                      "parallelIndex": 0,
                      "status": "passed",
                      "duration": 1575,
                      "errors": [],
                      "stdout": [],
                      "stderr": [],
                      "retry": 0,
                      "startTime": "2026-03-16T02:44:58.027Z",
                      "annotations": [],
                      "attachments": [
                        {
                          "name": "screenshot",
                          "contentType": "image/png",
                          "path": "/home/user/ScholarSync-/test-results/compliance-spec-016-compli-85f1c-etsx-has-no-stale-response--qa-chromium/test-finished-1.png"
                        }
                      ]
                    }
                  ],
                  "status": "expected"
                }
              ],
              "id": "f49594e98bf0294642a8-aa7179302e57dd0fdb16",
              "file": "compliance/spec-016.spec.ts",
              "line": 399,
              "column": 3
            }
          ]
        }
      ]
    }
  ],
  "errors": [],
  "stats": {
    "startTime": "2026-03-16T02:44:40.178Z",
    "duration": 19943.691000000003,
    "expected": 8,
    "skipped": 0,
    "unexpected": 0,
    "flaky": 0
  }
}